prefect_fugue/__init__.py
prefect_fugue/_utils.py
prefect_fugue/_version.py
prefect_fugue/blocks.py
prefect_fugue/registry.py
prefect_fugue-0.0.3.dist-info/LICENSE
prefect_fugue-0.0.3.dist-info/METADATA
prefect_fugue-0.0.3.dist-info/WHEEL
prefect_fugue-0.0.3.dist-info/entry_points.txt
prefect_fugue-0.0.3.dist-info/top_level.txt
prefect_fugue-0.0.3.dist-info/RECORD
